rv_script_lib/__init__.py
rv_script_lib/_version.py
rv_script_lib/arguments.py
rv_script_lib/healthchecks.py
rv_script_lib/lib_types.py
rv_script_lib/logging.py
rv_script_utils-0.2.1.dist-info/LICENSE
rv_script_utils-0.2.1.dist-info/METADATA
rv_script_utils-0.2.1.dist-info/WHEEL
rv_script_utils-0.2.1.dist-info/top_level.txt
rv_script_utils-0.2.1.dist-info/RECORD
