Metadata-Version: 2.1
Name: rv-script-utils
Version: 0.2.1
Summary: Utilities to help make scripts
License: MIT License
Project-URL: Homepage, https://github.com/rveachkc/rv-script-utils
Keywords: script,logging,healthchecks.io
Classifier: Development Status :: 3 - Alpha
Classifier: Intended Audience :: Developers
Classifier: License :: OSI Approved :: MIT License
Classifier: Programming Language :: Python :: 3
Requires-Python: >=3.12
License-File: LICENSE
Requires-Dist: prometheus-client>=0.21.1
Requires-Dist: pytimeparse>=1.1.8
Requires-Dist: requests>=2.32.3
Requires-Dist: structlog>=24.4.0
